mck/__init__.py
mck/add_numbers.py
mck-0.0.1.dist-info/METADATA
mck-0.0.1.dist-info/WHEEL
mck-0.0.1.dist-info/licenses/LICENSE.txt
mck-0.0.1.dist-info/RECORD
