Metadata-Version: 2.4
Name: mck
Version: 0.0.1
Summary: this is a python package that add numbers
Project-URL: Documentation, https://github.com/Maaruuuf/mck#readme
Project-URL: Issues, https://github.com/Maaruuuf/mck/issues
Project-URL: Source, https://github.com/Maaruuuf/mck
Author-email: Maaruuuf <abc.maruf12@gmail.com>
License-Expression: MIT
License-File: LICENSE.txt
Classifier: Development Status :: 4 - Beta
Classifier: Programming Language :: Python
Classifier: Programming Language :: Python :: 3.10
Classifier: Programming Language :: Python :: 3.11
Classifier: Programming Language :: Python :: 3.12
Requires-Python: >=3.10
